Workbook

Sheet Anleitung
A1: Gewinnrechner – Anleitung
A2: 1. Blatt "Annahmen": gelbe Felder mit echten Werten füllen (Steuerstatus, Gebühren, Fixkosten, erwartete Bestellungen, Retouren).
A3: 2. Blatt "Gewinnrechner": pro Produkt eine Zeile, nur die gelben Spalten A–F ausfüllen. Platz für 30 Produkte.
A4: 3. Die Zeilen 5–7 sind Beispiele mit erfundenen Zahlen. Überschreiben oder löschen.
A5: 4. Spalte "Bewertung": Verlust (rot), knapp = unter 15 % Marge (orange), ok (grün).
A7: Farben: blaue Schrift auf Gelb = Eingabe · schwarz = Formel · grün = Wert aus dem Blatt "Annahmen".
A8: Wichtig: Alle Beispielwerte (Gebühren, Kosten, Bestellmengen) sind Platzhalter. Das Ergebnis ist eine Schätzung vor Einkommensteuer, keine Steuer- oder Finanzberatung.
A9: Steuerliche Annahmen (Umsatzsteuer, Vorsteuer, Kleinunternehmer) mit einem Steuerberater prüfen.

Sheet Annahmen
A1: Annahmen (gelten für alle Produkte)
A2: Gelb hinterlegte, blaue Werte sind Eingaben – bitte mit echten Werten ersetzen. Alle Beispielwerte sind Platzhalter, keine geprüften Konditionen.
A4: Annahme | B4: Wert | C4: Hinweis / Quelle
A5: Kleinunternehmer (Ja/Nein) | B5: Nein | C5: Bei "Ja" wird keine Umsatzsteuer abgezogen (Annahme: Kleinunternehmerregelung). Mit Steuerberater klären.
A6: Umsatzsteuersatz | B6: 0.19 | C6: Regelsatz Deutschland 19 %. Ob für einzelne Produkte ein anderer Satz gilt, mit Steuerberater klären.
A7: Zahlungsgebühr in % vom Bruttobetrag | B7: 0.029 | C7: BEISPIELWERT. Echte Gebühr beim gewählten Zahlungsanbieter / Shopify-Tarif prüfen.
A8: Zahlungsgebühr fix pro Bestellung (€) | B8: 0.25 | C8: BEISPIELWERT. Beim Zahlungsanbieter prüfen.
A9: Shopify-Monatsgebühr (€) | B9: 33 | C9: Laut Vergleichsportal (qualimero.com, 2026) Basic ca. 33 € netto/Monat bei monatlicher Zahlung. Auf shopify.com/de prüfen.
A10: Weitere feste Monatskosten (€) | B10: 20 | C10: BEISPIELWERT, z. B. Apps, Rechtstexte-Abo, Domain anteilig.
A11: Erwartete Bestellungen pro Monat | B11: 30 | C11: BEISPIELWERT. Verteilt die festen Kosten auf jede Bestellung.
A12: Retourenquote | B12: 0.1 | C12: BEISPIELWERT. Anteil der Bestellungen, die zurückkommen.
A13: Kosten pro Retoure (€) | B13: 6 | C13: BEISPIELWERT, z. B. Rücksendeetikett, nicht wiederverkaufbare Ware anteilig.
A15: Feste Kosten pro Bestellung (€) | B15: =IF(B11>0,(B9+B10)/B11,0) -> 1.7666667 | C15: Berechnet: (Shopify + weitere Fixkosten) / Bestellungen pro Monat
A16: Retourenkosten pro Bestellung (€) | B16: =B12*B13 -> 0.6 | C16: Berechnet: Retourenquote × Kosten pro Retoure

Sheet Gewinnrechner
A1: Gewinnrechner pro Produkt (eine Bestellung = ein Stück)
A2: Eingaben: gelbe Felder mit blauer Schrift (Spalten A–F). Alles andere wird berechnet. Zeilen 5–7 sind BEISPIELE mit erfundenen Zahlen – überschreiben oder löschen.
A4: Produkt | B4: Anbieter / Link | C4: Verkaufspreis brutto (€) | D4: Versand vom Kunden brutto (€) | E4: Einkauf inkl. Versand an Kunde (€) | F4: Werbekosten pro Bestellung (€) | G4: Umsatz netto (€) | H4: Zahlungsgebühr (€) | I4: Fixkosten-Anteil (€) | J4: Retouren-Anteil (€) | K4: Gewinn pro Bestellung (€) | L4: Marge (vom Nettoumsatz) | M4: Bewertung
A5: BEISPIEL Hunde-Hoodie (Print on Demand) | B5: z. B. Printify | C5: 34.9 | D5: 0 | E5: 18.5 | F5: 4 | G5: =IF(C5="","",IF(Annahmen!$B$5="Ja",C5+D5,(C5+D5)/(1+Annahmen!$B$6))) -> 29.327731 | H5: =IF(C5="","",(C5+D5)*Annahmen!$B$7+Annahmen!$B$8) -> 1.2621 | I5: =IF(C5="","",Annahmen!$B$15) -> 1.7666667 | J5: =IF(C5="","",Annahmen!$B$16) -> 0.6 | K5: =IF(C5="","",G5-E5-F5-H5-I5-J5) -> 3.1989644 | L5: =IF(C5="","",IF(G5>0,K5/G5,0)) -> 0.10907644 | M5: =IF(C5="","",IF(K5<0,"Verlust",IF(L5<0.15,"knapp","ok"))) -> knapp
A6: BEISPIEL Pfotenschuhe 4er-Set (Dropshipping) | B6: z. B. CJdropshipping | C6: 29.9 | D6: 4.9 | E6: 12 | F6: 5 | G6: =IF(C6="","",IF(Annahmen!$B$5="Ja",C6+D6,(C6+D6)/(1+Annahmen!$B$6))) -> 29.243697 | H6: =IF(C6="","",(C6+D6)*Annahmen!$B$7+Annahmen!$B$8) -> 1.2592 | I6: =IF(C6="","",Annahmen!$B$15) -> 1.7666667 | J6: =IF(C6="","",Annahmen!$B$16) -> 0.6 | K6: =IF(C6="","",G6-E6-F6-H6-I6-J6) -> 8.6178308 | L6: =IF(C6="","",IF(G6>0,K6/G6,0)) -> 0.29469019 | M6: =IF(C6="","",IF(K6<0,"Verlust",IF(L6<0.15,"knapp","ok"))) -> ok
A7: BEISPIEL Hundehalstuch (Print on Demand) | B7: z. B. Printful | C7: 19.9 | D7: 0 | E7: 11 | F7: 3 | G7: =IF(C7="","",IF(Annahmen!$B$5="Ja",C7+D7,(C7+D7)/(1+Annahmen!$B$6))) -> 16.722689 | H7: =IF(C7="","",(C7+D7)*Annahmen!$B$7+Annahmen!$B$8) -> 0.8271 | I7: =IF(C7="","",Annahmen!$B$15) -> 1.7666667 | J7: =IF(C7="","",Annahmen!$B$16) -> 0.6 | K7: =IF(C7="","",G7-E7-F7-H7-I7-J7) -> -0.47107759 | L7: =IF(C7="","",IF(G7>0,K7/G7,0)) -> -0.028169966 | M7: =IF(C7="","",IF(K7<0,"Verlust",IF(L7<0.15,"knapp","ok"))) -> Verlust
G8: =IF(C8="","",IF(Annahmen!$B$5="Ja",C8+D8,(C8+D8)/(1+Annahmen!$B$6))) | H8: =IF(C8="","",(C8+D8)*Annahmen!$B$7+Annahmen!$B$8) | I8: =IF(C8="","",Annahmen!$B$15) | J8: =IF(C8="","",Annahmen!$B$16) | K8: =IF(C8="","",G8-E8-F8-H8-I8-J8) | L8: =IF(C8="","",IF(G8>0,K8/G8,0)) | M8: =IF(C8="","",IF(K8<0,"Verlust",IF(L8<0.15,"knapp","ok")))
G9: =IF(C9="","",IF(Annahmen!$B$5="Ja",C9+D9,(C9+D9)/(1+Annahmen!$B$6))) | H9: =IF(C9="","",(C9+D9)*Annahmen!$B$7+Annahmen!$B$8) | I9: =IF(C9="","",Annahmen!$B$15) | J9: =IF(C9="","",Annahmen!$B$16) | K9: =IF(C9="","",G9-E9-F9-H9-I9-J9) | L9: =IF(C9="","",IF(G9>0,K9/G9,0)) | M9: =IF(C9="","",IF(K9<0,"Verlust",IF(L9<0.15,"knapp","ok")))
G10: =IF(C10="","",IF(Annahmen!$B$5="Ja",C10+D10,(C10+D10)/(1+Annahmen!$B$6))) | H10: =IF(C10="","",(C10+D10)*Annahmen!$B$7+Annahmen!$B$8) | I10: =IF(C10="","",Annahmen!$B$15) | J10: =IF(C10="","",Annahmen!$B$16) | K10: =IF(C10="","",G10-E10-F10-H10-I10-J10) | L10: =IF(C10="","",IF(G10>0,K10/G10,0)) | M10: =IF(C10="","",IF(K10<0,"Verlust",IF(L10<0.15,"knapp","ok")))
G11: =IF(C11="","",IF(Annahmen!$B$5="Ja",C11+D11,(C11+D11)/(1+Annahmen!$B$6))) | H11: =IF(C11="","",(C11+D11)*Annahmen!$B$7+Annahmen!$B$8) | I11: =IF(C11="","",Annahmen!$B$15) | J11: =IF(C11="","",Annahmen!$B$16) | K11: =IF(C11="","",G11-E11-F11-H11-I11-J11) | L11: =IF(C11="","",IF(G11>0,K11/G11,0)) | M11: =IF(C11="","",IF(K11<0,"Verlust",IF(L11<0.15,"knapp","ok")))
G12: =IF(C12="","",IF(Annahmen!$B$5="Ja",C12+D12,(C12+D12)/(1+Annahmen!$B$6))) | H12: =IF(C12="","",(C12+D12)*Annahmen!$B$7+Annahmen!$B$8) | I12: =IF(C12="","",Annahmen!$B$15) | J12: =IF(C12="","",Annahmen!$B$16) | K12: =IF(C12="","",G12-E12-F12-H12-I12-J12) | L12: =IF(C12="","",IF(G12>0,K12/G12,0)) | M12: =IF(C12="","",IF(K12<0,"Verlust",IF(L12<0.15,"knapp","ok")))
G13: =IF(C13="","",IF(Annahmen!$B$5="Ja",C13+D13,(C13+D13)/(1+Annahmen!$B$6))) | H13: =IF(C13="","",(C13+D13)*Annahmen!$B$7+Annahmen!$B$8) | I13: =IF(C13="","",Annahmen!$B$15) | J13: =IF(C13="","",Annahmen!$B$16) | K13: =IF(C13="","",G13-E13-F13-H13-I13-J13) | L13: =IF(C13="","",IF(G13>0,K13/G13,0)) | M13: =IF(C13="","",IF(K13<0,"Verlust",IF(L13<0.15,"knapp","ok")))
G14: =IF(C14="","",IF(Annahmen!$B$5="Ja",C14+D14,(C14+D14)/(1+Annahmen!$B$6))) | H14: =IF(C14="","",(C14+D14)*Annahmen!$B$7+Annahmen!$B$8) | I14: =IF(C14="","",Annahmen!$B$15) | J14: =IF(C14="","",Annahmen!$B$16) | K14: =IF(C14="","",G14-E14-F14-H14-I14-J14) | L14: =IF(C14="","",IF(G14>0,K14/G14,0)) | M14: =IF(C14="","",IF(K14<0,"Verlust",IF(L14<0.15,"knapp","ok")))
G15: =IF(C15="","",IF(Annahmen!$B$5="Ja",C15+D15,(C15+D15)/(1+Annahmen!$B$6))) | H15: =IF(C15="","",(C15+D15)*Annahmen!$B$7+Annahmen!$B$8) | I15: =IF(C15="","",Annahmen!$B$15) | J15: =IF(C15="","",Annahmen!$B$16) | K15: =IF(C15="","",G15-E15-F15-H15-I15-J15) | L15: =IF(C15="","",IF(G15>0,K15/G15,0)) | M15: =IF(C15="","",IF(K15<0,"Verlust",IF(L15<0.15,"knapp","ok")))
G16: =IF(C16="","",IF(Annahmen!$B$5="Ja",C16+D16,(C16+D16)/(1+Annahmen!$B$6))) | H16: =IF(C16="","",(C16+D16)*Annahmen!$B$7+Annahmen!$B$8) | I16: =IF(C16="","",Annahmen!$B$15) | J16: =IF(C16="","",Annahmen!$B$16) | K16: =IF(C16="","",G16-E16-F16-H16-I16-J16) | L16: =IF(C16="","",IF(G16>0,K16/G16,0)) | M16: =IF(C16="","",IF(K16<0,"Verlust",IF(L16<0.15,"knapp","ok")))
G17: =IF(C17="","",IF(Annahmen!$B$5="Ja",C17+D17,(C17+D17)/(1+Annahmen!$B$6))) | H17: =IF(C17="","",(C17+D17)*Annahmen!$B$7+Annahmen!$B$8) | I17: =IF(C17="","",Annahmen!$B$15) | J17: =IF(C17="","",Annahmen!$B$16) | K17: =IF(C17="","",G17-E17-F17-H17-I17-J17) | L17: =IF(C17="","",IF(G17>0,K17/G17,0)) | M17: =IF(C17="","",IF(K17<0,"Verlust",IF(L17<0.15,"knapp","ok")))
G18: =IF(C18="","",IF(Annahmen!$B$5="Ja",C18+D18,(C18+D18)/(1+Annahmen!$B$6))) | H18: =IF(C18="","",(C18+D18)*Annahmen!$B$7+Annahmen!$B$8) | I18: =IF(C18="","",Annahmen!$B$15) | J18: =IF(C18="","",Annahmen!$B$16) | K18: =IF(C18="","",G18-E18-F18-H18-I18-J18) | L18: =IF(C18="","",IF(G18>0,K18/G18,0)) | M18: =IF(C18="","",IF(K18<0,"Verlust",IF(L18<0.15,"knapp","ok")))
G19: =IF(C19="","",IF(Annahmen!$B$5="Ja",C19+D19,(C19+D19)/(1+Annahmen!$B$6))) | H19: =IF(C19="","",(C19+D19)*Annahmen!$B$7+Annahmen!$B$8) | I19: =IF(C19="","",Annahmen!$B$15) | J19: =IF(C19="","",Annahmen!$B$16) | K19: =IF(C19="","",G19-E19-F19-H19-I19-J19) | L19: =IF(C19="","",IF(G19>0,K19/G19,0)) | M19: =IF(C19="","",IF(K19<0,"Verlust",IF(L19<0.15,"knapp","ok")))
... G34: =IF(C34="","",IF(Annahmen!$B$5="Ja",C34+D34,(C34+D34)/(1+Annahmen!$B$6))) | H34: =IF(C34="","",(C34+D34)*Annahmen!$B$7+Annahmen!$B$8) | I34: =IF(C34="","",Annahmen!$B$15) | J34: =IF(C34="","",Annahmen!$B$16) | K34: =IF(C34="","",G34-E34-F34-H34-I34-J34) | L34: =IF(C34="","",IF(G34>0,K34/G34,0)) | M34: =IF(C34="","",IF(K34<0,"Verlust",IF(L34<0.15,"knapp","ok")))
